gallama/__init__.py
gallama/app.py
gallama/cli.py
gallama/dependencies.py
gallama/dependencies_server.py
gallama/server.py
gallama/api_response/__init__.py
gallama/api_response/chat_response.py
gallama/api_response/stream_parser.py
gallama/backend/__init__.py
gallama/backend/embedding/__init__.py
gallama/backend/embedding/embedding.py
gallama/backend/llm/__init__.py
gallama/backend/llm/format_enforcer.py
gallama/backend/llm/prompt_engine.py
gallama/backend/llm/thinking_template.py
gallama/backend/llm/tools.py
gallama/backend/llm/engine/__init__.py
gallama/backend/llm/engine/base.py
gallama/backend/llm/engine/exllama/__init__.py
gallama/backend/llm/engine/exllama/exllamav2.py
gallama/backend/llm/engine/exllama/inference_json_lmfe_wrapper.py
gallama/backend/llm/engine/llamacpp/__init__.py
gallama/backend/llm/engine/llamacpp/llamacpp.py
gallama/backend/llm/engine/mlx_vllm/__init__.py
gallama/backend/llm/engine/mlx_vllm/mlx_vlm.py
gallama/backend/llm/engine/transformers/__init__.py
gallama/backend/llm/engine/transformers/transformers.py
gallama/backend/llm/engine/transformers/model_support/__init__.py
gallama/backend/llm/engine/transformers/model_support/llama3_2_vision/__init__.py
gallama/backend/llm/engine/transformers/model_support/llama3_2_vision/text_streamer.py
gallama/backend/stt/__init__.py
gallama/backend/stt/asr_processor.py
gallama/backend/stt/audio_buffer.py
gallama/backend/stt/base.py
gallama/backend/stt/hypothesis.py
gallama/backend/stt/vad.py
gallama/backend/stt/faster_whisper/model.py
gallama/backend/stt/mlx_whisper/model.py
gallama/backend/tts/TTSQueueHandler.py
gallama/backend/tts/__init__.py
gallama/backend/tts/base.py
gallama/backend/tts/text_processor.py
gallama/backend/tts/model/__init__.py
gallama/backend/tts/model/gpt_sovits.py
gallama/backend/tts/model/gpt_sovits_source/__init__.py
gallama/backend/tts/model/gpt_sovits_source/GPT_SoVITS/__init__.py
gallama/backend/tts/model/gpt_sovits_source/GPT_SoVITS/download.py
gallama-0.0.9.dist-info/METADATA
gallama-0.0.9.dist-info/WHEEL
gallama-0.0.9.dist-info/entry_points.txt
gallama-0.0.9.dist-info/top_level.txt
gallama-0.0.9.dist-info/RECORD
