Metadata-Version: 2.4
Name: gallama
Version: 0.0.9
Summary: An opinionated Llama Server engine with a focus on agentic tasks
Author-email: David <trantrungduc91@example.com>
License: MIT
Project-URL: Homepage, https://github.com/remichu-ai/gallama
Requires-Python: >=3.11
Requires-Dist: cmake
Requires-Dist: samplerate
Requires-Dist: packaging
Requires-Dist: ninja
Requires-Dist: torch>=2.2.0
Requires-Dist: torchvision
Requires-Dist: accelerate
Requires-Dist: pydantic
Requires-Dist: pillow>=10.0.0
Requires-Dist: pytest
Requires-Dist: httpx
Requires-Dist: uvicorn
Requires-Dist: sentence-transformers
Requires-Dist: lm-format-enforcer
Requires-Dist: huggingface-hub
Requires-Dist: chardet
Requires-Dist: sse_starlette
Requires-Dist: fastapi
Requires-Dist: lxml
Requires-Dist: infinity-emb[all]
Requires-Dist: colorama
Requires-Dist: pyyaml
Requires-Dist: rich
Requires-Dist: pyzmq
Requires-Dist: pygments
Requires-Dist: httpx
Requires-Dist: psutil
Requires-Dist: formatron>=0.4.4
Requires-Dist: referencing
Requires-Dist: qwen_vl_utils
Requires-Dist: websockets>=14.1
Requires-Dist: scipy
Requires-Dist: datamodel-code-generator
Requires-Dist: python-multipart
Requires-Dist: silero-vad
Requires-Dist: faster-whisper
Requires-Dist: librosa
Requires-Dist: soundfile
Requires-Dist: ffmpeg-python
Requires-Dist: fuzzywuzzy
Requires-Dist: split-lang
Requires-Dist: numpy
Requires-Dist: kokoro
Requires-Dist: misaki
Requires-Dist: misaki[en]
Requires-Dist: misaki[ja]
Requires-Dist: misaki[ko]
Requires-Dist: misaki[zh]
Requires-Dist: livekit>=0.20.2
Requires-Dist: livekit-protocol
Requires-Dist: livekit-agents>=0.12.15
